rpa_captcha/__init__.py
rpa_captcha/api/__init__.py
rpa_captcha/command/__init__.py
rpa_captcha/command/bill/__init__.py
rpa_captcha/command/bill/service/__init__.py
rpa_captcha/request/__init__.py
rpa_captcha/service/__init__.py
rpa_captcha-1.0.0.dist-info/LICENSE
rpa_captcha-1.0.0.dist-info/METADATA
rpa_captcha-1.0.0.dist-info/WHEEL
rpa_captcha-1.0.0.dist-info/top_level.txt
rpa_captcha-1.0.0.dist-info/RECORD
